{
  "lang": "el",
  "name": "Ελληνικά",
  "language": "Γλώσσα:",
  "search": "Φιλτράρισμα ανά λέξη-κλειδί",
  "shared": {
    "explanation": "Εξήγηση",
    "option": "Επιλογή",
    "optionsApp": "Ρύθμιση εφαρμογής",
    "optionsCongSync": "Ρύθμιση συγχρονισμού εκκλησίας",
    "optionsMedia": "Ρύθμιση πολυμέσων",
    "optionsMeetings": "Ρύθμιση συνάθροισης",
    "password": "Κωδικός",
    "port": "Θύρα",
    "setting": "Ρύθμιση"
  },
  "home": {
    "expand": "Ανάπτυξη όλων των άρθρων",
    "collapse": "Σύμπτυξη όλων των άρθρων",
    "syncInProgress": "Συγχρονισμός μέσων συνάθροισης σε εξέλιξη",
    "mainScreen": "Κύρια οθόνη",
    "chooseWeek": "Επιλέξτε μια εβδομάδα",
    "syncComplete": "Συγχρονισμός ολοκληρώθηκε!",
    "musicPlaying": "Παίζει μουσική πριν και μετά τη συνάθροιση"
  },
  "manage-media": {
    "imgAddSong": "Προσθέτοντας ένα τραγούδι για μια δημόσια ομιλία",
    "imgAddPic": "Προσθέτοντας μια πρόσθετη εικόνα",
    "imgImportJWPUB": "Εισαγωγή πολυμέσων από μια ενότητα σε ένα αρχείο JWPUB",
    "imgPreviewJWPUB": "Προεπισκόπηση πολυμέσων από αρχείο JWPUB πριν από την εισαγωγή",
    "imgRename": "Μετονομασία αρχείου πολυμέσων"
  },
  "present-media": {
    "imgButton": "Μπλε κουμπί αναπαραγωγής για να μπείτε στη λειτουργία ελέγχου μέσων",
    "imgSelectMeeting": "Επιλογή συνάθροισης για την εμφάνιση πολυμέσων",
    "imgBG": "Προεπιλεγμένο φόντο πολυμέσων, με αυτόματα παραγόμενο εδάφιο έτους",
    "imgMediaList": "Λίστα μέσων που είναι έτοιμα να παρουσιαστούν",
    "imgStandby": "M³ παρουσίαση πολυμέσων σε κατάσταση αναμονής",
    "imgDisplayPic": "Εμφάνιση εικόνας",
    "imgPlayVideo": "Αναπαραγωγή βίντεο",
    "imgVideoScrub": "Μετακίνηση σε μια συγκεκριμένη ώρα σε ένα βίντεο"
  }
}
